pwc/__init__.py
pwc/version.py
pwc-0.0.2.dist-info/LICENSE
pwc-0.0.2.dist-info/METADATA
pwc-0.0.2.dist-info/WHEEL
pwc-0.0.2.dist-info/top_level.txt
pwc-0.0.2.dist-info/RECORD
