Metadata-Version: 2.1
Name: pwc
Version: 0.0.2
Summary: By Papers with Code
Home-page: UNKNOWN
Author: Papers with Code
Maintainer: Papers with Code
License: Apache-2.0
Platform: Windows
Platform: POSIX
Platform: MacOSX
Classifier: Programming Language :: Python :: 3
Classifier: Programming Language :: Python :: 3.6
Classifier: Programming Language :: Python :: 3.7
Classifier: License :: OSI Approved :: Apache Software License
Classifier: Operating System :: OS Independent
